{
  "Palette": {
    "01-Neutral": {
      "0": {
        "value": "#000000",
        "type": "color"
      },
      "50": {
        "value": "#141414",
        "type": "color"
      },
      "100": {
        "value": "#242424",
        "type": "color"
      },
      "200": {
        "value": "#4d4d4d",
        "type": "color"
      },
      "300": {
        "value": "#626262",
        "type": "color"
      },
      "400": {
        "value": "#8c8c8c",
        "type": "color"
      },
      "500": {
        "value": "#a5a5a5",
        "type": "color"
      },
      "600": {
        "value": "#bfbfbf",
        "type": "color"
      },
      "700": {
        "value": "#d9d9d9",
        "type": "color"
      },
      "800": {
        "value": "#e6e6e6",
        "type": "color"
      },
      "900": {
        "value": "#f5f5f5",
        "type": "color"
      },
      "1000": {
        "value": "#ffffff",
        "type": "color"
      }
    },
    "02-Blue": {
      "100": {
        "value": "#003357",
        "type": "color"
      },
      "200": {
        "value": "#003b66",
        "type": "color"
      },
      "300": {
        "value": "#005899",
        "type": "color"
      },
      "400": {
        "value": "#146bb8",
        "type": "color"
      },
      "500": {
        "value": "#5294e0",
        "type": "color"
      },
      "600": {
        "value": "#75aaf0",
        "type": "color"
      },
      "700": {
        "value": "#acd6eb",
        "type": "color"
      },
      "800": {
        "value": "#d9e2f2",
        "type": "color"
      },
      "900": {
        "value": "#ebf2fe",
        "type": "color"
      }
    },
    "03-Red": {
      "100": {
        "value": "#5c100a",
        "type": "color"
      },
      "200": {
        "value": "#8a170f",
        "type": "color"
      },
      "300": {
        "value": "#b71f14",
        "type": "color"
      },
      "400": {
        "value": "#de2317",
        "type": "color"
      },
      "500": {
        "value": "#eb5247",
        "type": "color"
      },
      "600": {
        "value": "#f07d75",
        "type": "color"
      },
      "700": {
        "value": "#f5a9a3",
        "type": "color"
      },
      "800": {
        "value": "#fad4d1",
        "type": "color"
      },
      "900": {
        "value": "#fdedec",
        "type": "color"
      }
    },
    "04-Green": {
      "100": {
        "value": "#1f4737",
        "type": "color"
      },
      "200": {
        "value": "#2e6b53",
        "type": "color"
      },
      "300": {
        "value": "#3d8f6e",
        "type": "color"
      },
      "400": {
        "value": "#45a184",
        "type": "color"
      },
      "500": {
        "value": "#65bd9a",
        "type": "color"
      },
      "600": {
        "value": "#89cdb2",
        "type": "color"
      },
      "700": {
        "value": "#a6d9c4",
        "type": "color"
      },
      "800": {
        "value": "#dbf0e8",
        "type": "color"
      },
      "900": {
        "value": "#f1f9f5",
        "type": "color"
      }
    },
    "05-Yellow": {
      "100": {
        "value": "#473e1f",
        "type": "color"
      },
      "200": {
        "value": "#997400",
        "type": "color"
      },
      "300": {
        "value": "#b88b00",
        "type": "color"
      },
      "400": {
        "value": "#cc9b00",
        "type": "color"
      },
      "500": {
        "value": "#ffc200",
        "type": "color"
      },
      "600": {
        "value": "#ffcf33",
        "type": "color"
      },
      "700": {
        "value": "#ffe180",
        "type": "color"
      },
      "800": {
        "value": "#fcf3cf",
        "type": "color"
      },
      "900": {
        "value": "#fffaeb",
        "type": "color"
      }
    },
    "06-Brown": {
      "100": {
        "value": "#29241f",
        "type": "color"
      },
      "200": {
        "value": "#574e42",
        "type": "color"
      },
      "300": {
        "value": "#746858",
        "type": "color"
      },
      "400": {
        "value": "#9c8e7c",
        "type": "color"
      },
      "500": {
        "value": "#b2a799",
        "type": "color"
      },
      "600": {
        "value": "#c8c0b6",
        "type": "color"
      },
      "700": {
        "value": "#ded9d3",
        "type": "color"
      },
      "800": {
        "value": "#e9e6e2",
        "type": "color"
      },
      "900": {
        "value": "#f6f5f3",
        "type": "color"
      }
    }
  },
  "Desktop": {
    "base": {
      "value": "16",
      "type": "sizing"
    },
    "xx-small": {
      "value": "{base}*0.25",
      "type": "sizing"
    },
    "x-small": {
      "value": "{base}*0.5",
      "type": "sizing"
    },
    "small": {
      "value": "{base}*0.75",
      "type": "sizing"
    },
    "default": {
      "value": "{base}",
      "type": "sizing"
    },
    "default[+4]": {
      "value": "{base}+4px",
      "type": "sizing"
    },
    "medium": {
      "value": "{base}*1.5",
      "type": "sizing"
    },
    "large": {
      "value": "{base}*2",
      "type": "sizing"
    },
    "x-large": {
      "value": "{base}*3",
      "type": "sizing"
    },
    "xx-large": {
      "value": "{base}*3.5",
      "type": "sizing"
    },
    "radius-default": {
      "value": "3px",
      "type": "borderRadius"
    },
    "radius-round": {
      "value": "{base}",
      "type": "borderRadius"
    },
    "radius-full": {
      "value": "100%",
      "type": "borderRadius"
    },
    "space-base": {
      "value": "16",
      "type": "spacing"
    },
    "space-xx-small": {
      "value": "{space-base}*0.25",
      "type": "spacing"
    },
    "space-x-small": {
      "value": "{space-base}*0.5",
      "type": "spacing"
    },
    "space-small": {
      "value": "{space-base}*0.75",
      "type": "spacing"
    },
    "space-default": {
      "value": "{space-base}",
      "type": "spacing"
    },
    "space-medium": {
      "value": "{space-base}*1.5",
      "type": "spacing"
    },
    "space-large": {
      "value": "{space-base}*2",
      "type": "spacing"
    },
    "space-x-large": {
      "value": "{space-base}*3",
      "type": "spacing"
    },
    "space-xx-large": {
      "value": "{space-base}*3.5",
      "type": "spacing"
    },
    "font-primary": {
      "value": "Madera",
      "type": "fontFamilies"
    },
    "weight-regular": {
      "value": "400",
      "type": "fontWeights"
    },
    "weight-medium": {
      "value": "500",
      "type": "fontWeights"
    },
    "weight-bold": {
      "value": "700",
      "type": "fontWeights"
    },
    "Base": {
      "font-base": {
        "value": "18",
        "type": "fontSizes"
      },
      "font-scale": {
        "value": "1.25",
        "type": "fontSizes"
      }
    },
    "font": {
      "xxx-large": {
        "value": "roundTo({Base.font-base}*{Base.font-scale}^5, 0)",
        "type": "fontSizes"
      },
      "xx-large": {
        "value": "roundTo({Base.font-base}*{Base.font-scale}^4, 0)",
        "type": "fontSizes"
      },
      "x-large": {
        "value": "roundTo({Base.font-base}*{Base.font-scale}^3, 0)",
        "type": "fontSizes"
      },
      "large": {
        "value": "roundTo({Base.font-base}*{Base.font-scale}^2, 0)",
        "type": "fontSizes"
      },
      "medium": {
        "value": "roundTo({Base.font-base}*{Base.font-scale}^1, 0)",
        "type": "fontSizes"
      },
      "small": {
        "value": "roundTo({Base.font-base}*0.8, 0)",
        "type": "fontSizes"
      },
      "x-small": {
        "value": "roundTo({Base.font-base}*0.67, 0)",
        "type": "fontSizes"
      }
    },
    "heading": {
      "page": {
        "value": {
          "fontFamily": "{font-primary}",
          "fontWeight": "{weight-bold}",
          "lineHeight": "120%",
          "fontSize": "{font.xxx-large}"
        },
        "type": "typography",
        "description": "Use for page title only. "
      },
      "xxx": {
        "value": {
          "fontFamily": "{font-primary}",
          "fontWeight": "{weight-bold}",
          "lineHeight": "120%",
          "fontSize": "{font.large}"
        },
        "type": "typography",
        "description": "Use for page title only. "
      },
      "x-large": {
        "value": {
          "fontFamily": "{font-primary}",
          "fontWeight": "{weight-bold}",
          "lineHeight": "120%",
          "fontSize": "{font.x-large}",
          "letterSpacing": "0"
        },
        "type": "typography",
        "description": "Use for page title only. "
      },
      "large": {
        "value": {
          "fontFamily": "{font-primary}",
          "fontWeight": "{weight-bold}",
          "lineHeight": "120%",
          "fontSize": "{font.large}",
          "letterSpacing": "0"
        },
        "type": "typography",
        "description": "Use for page title only. "
      },
      "section": {
        "value": {
          "fontFamily": "{font-primary}",
          "fontWeight": "{weight-bold}",
          "lineHeight": "120%",
          "fontSize": "{font.medium}",
          "letterSpacing": "0"
        },
        "type": "typography",
        "description": "Use for page title only. "
      },
      "inline": {
        "value": {
          "fontFamily": "{font-primary}",
          "fontWeight": "{weight-bold}",
          "lineHeight": "155.55555555%",
          "fontSize": "{Base.font-base}",
          "letterSpacing": "0"
        },
        "type": "typography",
        "description": "Use for page title only. "
      },
      "inline-copy": {
        "value": {
          "fontFamily": "{font-primary}",
          "fontWeight": "{weight-bold}",
          "lineHeight": "138.88888%",
          "fontSize": "{font.small}",
          "letterSpacing": "0"
        },
        "type": "typography",
        "description": "Use for page title only. "
      }
    },
    "text": {
      "large": {
        "value": {
          "fontFamily": "{font-primary}",
          "fontWeight": "{weight-regular}",
          "fontSize": "{font.medium}",
          "lineHeight": "160%",
          "letterSpacing": "0"
        },
        "type": "typography"
      },
      "body": {
        "value": {
          "fontFamily": "{font-primary}",
          "fontWeight": "{weight-regular}",
          "fontSize": "{Base.font-base}",
          "lineHeight": "160%",
          "letterSpacing": "0",
          "paragraphSpacing": "{space-default}"
        },
        "type": "typography"
      },
      "small": {
        "value": {
          "fontFamily": "{font-primary}",
          "fontWeight": "{weight-regular}",
          "fontSize": "{font.small}",
          "lineHeight": "160%",
          "letterSpacing": "0"
        },
        "type": "typography"
      },
      "x-small": {
        "value": {
          "fontFamily": "{font-primary}",
          "fontWeight": "{weight-regular}",
          "fontSize": "{font.x-small}",
          "lineHeight": "160%",
          "letterSpacing": "0"
        },
        "type": "typography"
      }
    },
    "label": {
      "large": {
        "value": {
          "fontFamily": "{font-primary}",
          "fontWeight": "{weight-medium}",
          "lineHeight": "{Base.font-base}*1.55555555",
          "fontSize": "{Base.font-base}"
        },
        "type": "typography"
      },
      "default": {
        "value": {
          "fontFamily": "{font-primary}",
          "fontWeight": "{weight-medium}",
          "lineHeight": "150%",
          "fontSize": "{Base.font-base}*0.88888888"
        },
        "type": "typography"
      },
      "small": {
        "value": {
          "fontFamily": "{font-primary}",
          "fontWeight": "{weight-medium}",
          "lineHeight": "20px",
          "fontSize": "{font.small}"
        },
        "type": "typography"
      },
      "x-small": {
        "value": {
          "fontFamily": "{font-primary}",
          "fontWeight": "{weight-medium}",
          "fontSize": "{font.x-small}",
          "lineHeight": "160%",
          "letterSpacing": "0"
        },
        "type": "typography"
      }
    }
  },
  "Mobile": {
    "base": {
      "value": "16",
      "type": "sizing"
    },
    "xx-small": {
      "value": "{base}*0.25",
      "type": "sizing"
    },
    "x-small": {
      "value": "{base}*0.5",
      "type": "sizing"
    },
    "small": {
      "value": "{base}*0.75",
      "type": "sizing"
    },
    "default": {
      "value": "{base}",
      "type": "sizing"
    },
    "default[+4]": {
      "value": "{base}+4px",
      "type": "sizing"
    },
    "medium": {
      "value": "{base}*1.25",
      "type": "sizing"
    },
    "large": {
      "value": "{base}*2",
      "type": "sizing"
    },
    "x-large": {
      "value": "{base}*3",
      "type": "sizing"
    },
    "xx-large": {
      "value": "{base}*3.5",
      "type": "sizing"
    },
    "radius-default": {
      "value": "3px",
      "type": "borderRadius"
    },
    "radius-round": {
      "value": "{base}",
      "type": "borderRadius"
    },
    "radius-full": {
      "value": "100%",
      "type": "borderRadius"
    },
    "space-base": {
      "value": "16",
      "type": "spacing"
    },
    "space-xx-small": {
      "value": "{space-base}*0.25",
      "type": "spacing"
    },
    "space-x-small": {
      "value": "{space-base}*0.5",
      "type": "spacing"
    },
    "space-small": {
      "value": "{space-base}*0.75",
      "type": "spacing"
    },
    "space-default": {
      "value": "{space-base}",
      "type": "spacing"
    },
    "space-medium": {
      "value": "{space-base}*1.25",
      "type": "spacing"
    },
    "space-large": {
      "value": "{space-base}*2",
      "type": "spacing"
    },
    "space-x-large": {
      "value": "{space-base}*2.5",
      "type": "spacing"
    },
    "space-xx-large": {
      "value": "{space-base}*3",
      "type": "spacing"
    },
    "font-primary": {
      "value": "Madera",
      "type": "fontFamilies"
    },
    "weight-regular": {
      "value": "400",
      "type": "fontWeights"
    },
    "weight-medium": {
      "value": "500",
      "type": "fontWeights"
    },
    "weight-bold": {
      "value": "700",
      "type": "fontWeights"
    },
    "Base": {
      "font-base": {
        "value": "16",
        "type": "fontSizes"
      },
      "font-scale": {
        "value": "1.2",
        "type": "fontSizes"
      }
    },
    "font": {
      "xxx-large": {
        "value": "roundTo({Base.font-base}*{Base.font-scale}^5, 0)",
        "type": "fontSizes"
      },
      "xx-large": {
        "value": "roundTo({Base.font-base}*{Base.font-scale}^4, 0)",
        "type": "fontSizes"
      },
      "x-large": {
        "value": "roundTo({Base.font-base}*{Base.font-scale}^3, 0)",
        "type": "fontSizes"
      },
      "large": {
        "value": "roundTo({Base.font-base}*{Base.font-scale}^2, 0)",
        "type": "fontSizes"
      },
      "medium": {
        "value": "roundTo({Base.font-base}*{Base.font-scale}, 0)",
        "type": "fontSizes"
      },
      "small": {
        "value": "roundTo({Base.font-base}*0.8, 0)",
        "type": "fontSizes"
      },
      "x-small": {
        "value": "roundTo({Base.font-base}*0.67, 0)",
        "type": "fontSizes"
      }
    },
    "heading": {
      "page": {
        "value": {
          "fontFamily": "{font-primary}",
          "fontWeight": "{weight-bold}",
          "lineHeight": "120%",
          "fontSize": "{font.xx-large}"
        },
        "type": "typography",
        "description": "Use for page title only. "
      },
      "xxx": {
        "value": {
          "fontFamily": "{font-primary}",
          "fontWeight": "{weight-bold}",
          "lineHeight": "120%",
          "fontSize": "{font.large}"
        },
        "type": "typography",
        "description": "Use for page title only. "
      },
      "x-large": {
        "value": {
          "fontFamily": "{font-primary}",
          "fontWeight": "{weight-bold}",
          "lineHeight": "120%",
          "fontSize": "{font.x-large}",
          "letterSpacing": "0"
        },
        "type": "typography",
        "description": "Use for page title only. "
      },
      "large": {
        "value": {
          "fontFamily": "{font-primary}",
          "fontWeight": "{weight-bold}",
          "lineHeight": "120%",
          "fontSize": "{font.large}",
          "letterSpacing": "0"
        },
        "type": "typography",
        "description": "Use for page title only. "
      },
      "section": {
        "value": {
          "fontFamily": "{font-primary}",
          "fontWeight": "{weight-bold}",
          "lineHeight": "120%",
          "fontSize": "{font.medium}",
          "letterSpacing": "0"
        },
        "type": "typography",
        "description": "Use for page title only. "
      },
      "inline": {
        "value": {
          "fontFamily": "{font-primary}",
          "fontWeight": "{weight-bold}",
          "lineHeight": "155.55555555%",
          "fontSize": "{Base.font-base}",
          "letterSpacing": "0"
        },
        "type": "typography",
        "description": "Use for page title only. "
      },
      "inline-copy": {
        "value": {
          "fontFamily": "{font-primary}",
          "fontWeight": "{weight-bold}",
          "lineHeight": "138.88888%",
          "fontSize": "{font.small}",
          "letterSpacing": "0"
        },
        "type": "typography",
        "description": "Use for page title only. "
      }
    },
    "text": {
      "large": {
        "value": {
          "fontFamily": "{font-primary}",
          "fontWeight": "{weight-regular}",
          "fontSize": "{font.medium}",
          "lineHeight": "160%",
          "letterSpacing": "0"
        },
        "type": "typography"
      },
      "body": {
        "value": {
          "fontFamily": "{font-primary}",
          "fontWeight": "{weight-regular}",
          "fontSize": "{Base.font-base}",
          "lineHeight": "160%",
          "letterSpacing": "0"
        },
        "type": "typography"
      },
      "small": {
        "value": {
          "fontFamily": "{font-primary}",
          "fontWeight": "{weight-regular}",
          "fontSize": "{font.small}",
          "lineHeight": "160%",
          "letterSpacing": "0"
        },
        "type": "typography"
      },
      "x-small": {
        "value": {
          "fontFamily": "{font-primary}",
          "fontWeight": "{weight-regular}",
          "fontSize": "{font.x-small}",
          "lineHeight": "160%",
          "letterSpacing": "0"
        },
        "type": "typography"
      }
    },
    "label": {
      "large": {
        "value": {
          "fontFamily": "{font-primary}",
          "fontWeight": "{weight-medium}",
          "lineHeight": "150%",
          "fontSize": "{Base.font-base}"
        },
        "type": "typography"
      },
      "default": {
        "value": {
          "fontFamily": "{font-primary}",
          "fontWeight": "{weight-medium}",
          "lineHeight": "155%",
          "fontSize": "{Base.font-base}*0.88888888"
        },
        "type": "typography"
      },
      "small": {
        "value": {
          "fontFamily": "{font-primary}",
          "fontWeight": "{weight-medium}",
          "lineHeight": "20px",
          "fontSize": "{font.small}"
        },
        "type": "typography"
      }
    },
    "padding": {
      "test": {
        "value": "24px",
        "type": "sizing"
      }
    }
  },
  "Light": {
    "Text": {
      "Standard": {
        "value": "{01-Neutral.100}",
        "type": "color",
        "description": "Use for primary text, such as body copy, sentence case headers, and buttons."
      },
      "Secondary": {
        "value": "{01-Neutral.200}",
        "type": "color"
      },
      "Subtle": {
        "value": "{01-Neutral.400}",
        "type": "color",
        "description": "Use for secondary text, such as navigation, subtle button links, input field labels, and all caps subheadings."
      },
      "Mute": {
        "value": "{01-Neutral.700}",
        "type": "color",
        "description": "Use for tertiary text, such as meta-data, breadcrumbs, input field placeholder and helper text."
      },
      "Inverse": {
        "value": "{01-Neutral.1000}",
        "type": "color",
        "description": "Use for text on bold backgrounds."
      },
      "Link": {
        "value": "{01-Neutral.100}",
        "type": "color"
      },
      "Accent": {
        "value": "{02-Blue.300}",
        "type": "color"
      },
      "Accent hover": {
        "value": "{02-Blue.200}",
        "type": "color"
      },
      "Critical": {
        "value": "{03-Red.300}",
        "type": "color",
        "description": "Use for critical text, such as input field error messaging."
      },
      "Success": {
        "value": "{04-Green.200}",
        "type": "color"
      },
      "Info": {
        "value": "{02-Blue.300}",
        "type": "color"
      },
      "Warning": {
        "value": "{05-Yellow.100}",
        "type": "color"
      },
      "Warning strong": {
        "value": "{05-Yellow.100}",
        "type": "color"
      }
    },
    "Icon": {
      "Standard": {
        "value": "{Text.Standard}",
        "type": "color"
      },
      "Secondary": {
        "value": "{Text.Secondary}",
        "type": "color"
      },
      "Subtle": {
        "value": "{Text.Subtle}",
        "type": "color"
      },
      "Mute": {
        "value": "{Text.Mute}",
        "type": "color"
      },
      "Inverse": {
        "value": "{Text.Inverse}",
        "type": "color"
      },
      "Link": {
        "value": "{Text.Link}",
        "type": "color"
      },
      "Accent": {
        "value": "{Text.Accent}",
        "type": "color"
      },
      "Critical": {
        "value": "{Text.Critical}",
        "type": "color"
      },
      "Success": {
        "value": "{Text.Success}",
        "type": "color"
      },
      "Info": {
        "value": "{Text.Info}",
        "type": "color"
      },
      "Warning": {
        "value": "{Text.Warning}",
        "type": "color"
      }
    },
    "Border": {
      "Standard": {
        "value": "{01-Neutral.300}",
        "type": "color"
      },
      "Subtle": {
        "value": "{01-Neutral.800}",
        "type": "color"
      },
      "Strong": {
        "value": "{01-Neutral.100}",
        "type": "color"
      },
      "Inverse": {
        "value": "{01-Neutral.900}",
        "type": "color"
      },
      "Accent": {
        "value": "{02-Blue.300}",
        "type": "color"
      },
      "Accent hover": {
        "value": "{02-Blue.200}",
        "type": "color"
      },
      "Critical": {
        "value": "{03-Red.300}",
        "type": "color"
      },
      "Success": {
        "value": "{04-Green.600}",
        "type": "color"
      },
      "Success hover": {
        "value": "{04-Green.400}",
        "type": "color"
      },
      "Info": {
        "value": "#75aaf0",
        "type": "color"
      },
      "Warning": {
        "value": "{05-Yellow.600}",
        "type": "color"
      }
    },
    "Background": {
      "Neutral": {
        "value": "{06-Brown.900}",
        "type": "color"
      },
      "Neutral hover": {
        "value": "{06-Brown.800}",
        "type": "color"
      },
      "Inverse": {
        "value": "{01-Neutral.100}",
        "type": "color"
      },
      "Focus": {
        "value": "{02-Blue.900}",
        "type": "color"
      },
      "Focus hover": {
        "value": "{02-Blue.800}",
        "type": "color"
      },
      "Accent": {
        "value": "{02-Blue.300}",
        "type": "color"
      },
      "Accent hover": {
        "value": "{02-Blue.200}",
        "type": "color"
      },
      "Critical": {
        "value": "{03-Red.900}",
        "type": "color"
      },
      "Critical hover": {
        "value": "{03-Red.800}",
        "type": "color"
      },
      "Critical strong": {
        "value": "{03-Red.300}",
        "type": "color"
      },
      "Critical strong hover": {
        "value": "{03-Red.200}",
        "type": "color"
      },
      "Success": {
        "value": "{04-Green.900}",
        "type": "color"
      },
      "Success hover": {
        "value": "{04-Green.800}",
        "type": "color"
      },
      "Success strong": {
        "value": "{04-Green.200}",
        "type": "color"
      },
      "Success strong hover": {
        "value": "{04-Green.100}",
        "type": "color"
      },
      "Info": {
        "value": "{02-Blue.900}",
        "type": "color"
      },
      "Info hover": {
        "value": "{02-Blue.800}",
        "type": "color"
      },
      "Info strong": {
        "value": "{02-Blue.300}",
        "type": "color"
      },
      "Info strong hover": {
        "value": "{02-Blue.200}",
        "type": "color"
      },
      "Warning": {
        "value": "{05-Yellow.900}",
        "type": "color"
      },
      "Warning hover": {
        "value": "{05-Yellow.800}",
        "type": "color"
      },
      "Warning strong": {
        "value": "{05-Yellow.600}",
        "type": "color"
      },
      "Warning strong hover": {
        "value": "{05-Yellow.500}",
        "type": "color"
      },
      "Canvas": {
        "value": "{01-Neutral.1000}",
        "type": "color"
      }
    },
    "Focus": {
      "value": [
        {
          "x": "0",
          "y": "0",
          "blur": "0",
          "spread": "3",
          "color": "{Background.Canvas}",
          "type": "dropShadow"
        },
        {
          "x": "0",
          "y": "0",
          "blur": "0",
          "spread": "6",
          "color": "#ADC6EB",
          "type": "dropShadow"
        }
      ],
      "type": "boxShadow"
    }
  },
  "Dark": {
    "Text": {
      "Standard": {
        "value": "{01-Neutral.900}",
        "type": "color",
        "description": "Use for primary text, such as body copy, sentence case headers, and buttons."
      },
      "Secondary": {
        "value": "{01-Neutral.700}",
        "type": "color"
      },
      "Subtle": {
        "value": "{01-Neutral.400}",
        "type": "color",
        "description": "Use for secondary text, such as navigation, subtle button links, input field labels, and all caps subheadings."
      },
      "Mute": {
        "value": "{01-Neutral.300}",
        "type": "color",
        "description": "Use for tertiary text, such as meta-data, breadcrumbs, input field placeholder and helper text."
      },
      "Inverse": {
        "value": "{01-Neutral.100}",
        "type": "color",
        "description": "Use for text on bold backgrounds."
      },
      "Link": {
        "value": "{01-Neutral.900}",
        "type": "color"
      },
      "Accent": {
        "value": "{02-Blue.600}",
        "type": "color"
      },
      "Accent hover": {
        "value": "#003b66",
        "type": "color"
      },
      "Critical": {
        "value": "{03-Red.800}",
        "type": "color",
        "description": "Use for critical text, such as input field error messaging."
      },
      "Success": {
        "value": "{04-Green.800}",
        "type": "color"
      },
      "Info": {
        "value": "{02-Blue.700}",
        "type": "color"
      },
      "Warning": {
        "value": "{05-Yellow.800}",
        "type": "color"
      },
      "Warning strong": {
        "value": "{05-Yellow.100}",
        "type": "color"
      }
    },
    "Icon": {
      "Standard": {
        "value": "{01-Neutral.900}",
        "type": "color"
      },
      "Secondary": {
        "value": "{01-Neutral.700}",
        "type": "color"
      },
      "Subtle": {
        "value": "#8c8c8c",
        "type": "color"
      },
      "Mute": {
        "value": "{01-Neutral.300}",
        "type": "color"
      },
      "Inverse": {
        "value": "{01-Neutral.100}",
        "type": "color"
      },
      "Link": {
        "value": "{01-Neutral.900}",
        "type": "color"
      },
      "Accent": {
        "value": "{02-Blue.600}",
        "type": "color"
      },
      "Critical": {
        "value": "{03-Red.800}",
        "type": "color"
      },
      "Success": {
        "value": "{04-Green.800}",
        "type": "color"
      },
      "Info": {
        "value": "{02-Blue.700}",
        "type": "color"
      },
      "Warning": {
        "value": "{05-Yellow.800}",
        "type": "color"
      }
    },
    "Border": {
      "Standard": {
        "value": "{01-Neutral.600}",
        "type": "color"
      },
      "Subtle": {
        "value": "{01-Neutral.600}",
        "type": "color"
      },
      "Strong": {
        "value": "{01-Neutral.900}",
        "type": "color"
      },
      "Inverse": {
        "value": "#ffffff",
        "type": "color"
      },
      "Accent": {
        "value": "{02-Blue.600}",
        "type": "color"
      },
      "Accent hover": {
        "value": "{02-Blue.800}",
        "type": "color"
      },
      "Critical": {
        "value": "#b71f14",
        "type": "color"
      },
      "Success": {
        "value": "{04-Green.500}",
        "type": "color"
      },
      "Info": {
        "value": "#75aaf0",
        "type": "color"
      },
      "Warning": {
        "value": "#ffce33",
        "type": "color"
      }
    },
    "Background": {
      "Neutral": {
        "value": "{01-Neutral.100}",
        "type": "color"
      },
      "Neutral hover": {
        "value": "{01-Neutral.200}",
        "type": "color"
      },
      "Inverse": {
        "value": "{01-Neutral.900}",
        "type": "color"
      },
      "Focus": {
        "value": "{02-Blue.200}",
        "type": "color"
      },
      "Focus hover": {
        "value": "{02-Blue.300}",
        "type": "color"
      },
      "Accent": {
        "value": "{02-Blue.600}",
        "type": "color"
      },
      "Accent hover": {
        "value": "{02-Blue.500}",
        "type": "color"
      },
      "Critical": {
        "value": "{03-Red.200}",
        "type": "color"
      },
      "Critical hover": {
        "value": "{03-Red.300}",
        "type": "color"
      },
      "Critical strong": {
        "value": "{03-Red.800}",
        "type": "color"
      },
      "Critical strong hover": {
        "value": "{03-Red.700}",
        "type": "color"
      },
      "Success": {
        "value": "{04-Green.200}",
        "type": "color"
      },
      "Success hover": {
        "value": "{04-Green.300}",
        "type": "color"
      },
      "Success strong": {
        "value": "{04-Green.600}",
        "type": "color"
      },
      "Info": {
        "value": "{02-Blue.200}",
        "type": "color"
      },
      "Info strong": {
        "value": "{02-Blue.600}",
        "type": "color"
      },
      "Warning": {
        "value": "{05-Yellow.100}",
        "type": "color"
      },
      "Warning hover": {
        "value": "{05-Yellow.200}",
        "type": "color"
      },
      "Warning strong": {
        "value": "{05-Yellow.800}",
        "type": "color"
      },
      "Canvas": {
        "value": "{01-Neutral.50}",
        "type": "color"
      }
    },
    "Focus": {
      "value": [
        {
          "x": "0",
          "y": "0",
          "blur": "0",
          "spread": "3",
          "color": "{Background.Canvas}",
          "type": "dropShadow"
        },
        {
          "x": "0",
          "y": "0",
          "blur": "0",
          "spread": "6",
          "color": "#d3ebae",
          "type": "dropShadow"
        }
      ],
      "type": "boxShadow"
    }
  },
  "$themes": [],
  "$metadata": {
    "tokenSetOrder": [
      "Palette",
      "Desktop",
      "Mobile",
      "Light",
      "Dark"
    ]
  }
}